face_utils/__init__.py
face_utils/cropping/__init__.py
face_utils/cropping/cropping.py
face_utils/detection/__init__.py
face_utils/detection/detectors.py
face_utils/detection/settings.py
face_utils/detection/__pycache__/__init__.cpython-37.pyc
face_utils/detection/__pycache__/cropping.cpython-37.pyc
face_utils/detection/__pycache__/settings.cpython-37.pyc
face_utils/detection/assets/Widerface-RetinaFace.caffemodel
face_utils/detection/assets/deploy.prototxt
face_utils/detection/assets/haarcascade_frontalface_default.xml
face_utils-0.1.0.dist-info/LICENSE
face_utils-0.1.0.dist-info/METADATA
face_utils-0.1.0.dist-info/WHEEL
face_utils-0.1.0.dist-info/top_level.txt
face_utils-0.1.0.dist-info/RECORD
