Metadata-Version: 2.1
Name: face-utils
Version: 0.1.0
Summary: opensource wrapper library for face detection algorithms and other utilities
Home-page: https://github.com/HermasTV/face_utils
Author: Hermas
Author-email: a7medhermas@gmail.com
License: MIT
Keywords: face_utils face-utils hermas digified python face utils datection
Platform: UNKNOWN
Classifier: Intended Audience :: Science/Research
Classifier: License :: OSI Approved :: MIT License
Classifier: Programming Language :: Python :: 3.7
Classifier: Topic :: Scientific/Engineering :: Artificial Intelligence 
Requires-Dist: cmake
Requires-Dist: opencv-python
Requires-Dist: face-recognition
